[
    {
        "id": 1,
        "first_name": "Francoise",
        "last_name": "Kocher",
        "email": "fkocher0@joomla.org",
        "Date_Of_Birth": "7/3/1987",
        "Age": 38,
        "Country": "China",
        "Phone": "5207087145"
    },
    {
        "id": 2,
        "first_name": "Verna",
        "last_name": "Dunphy",
        "email": "vdunphy1@github.io",
        "Date_Of_Birth": "4/18/1977",
        "Age": 93,
        "Country": "Russia",
        "Phone": "4796452514"
    },
    {
        "id": 3,
        "first_name": "Alfy",
        "last_name": "Petrovic",
        "email": "apetrovic2@facebook.com",
        "Date_Of_Birth": "11/2/1984",
        "Age": 60,
        "Country": "Sweden",
        "Phone": "2736239240"
    },
    {
        "id": 4,
        "first_name": "Sauveur",
        "last_name": "Heitz",
        "email": "sheitz3@about.com",
        "Date_Of_Birth": "10/8/1981",
        "Age": 44,
        "Country": "Sierra Leone",
        "Phone": "4065589691"
    },
    {
        "id": 5,
        "first_name": "Corrinne",
        "last_name": "Seligson",
        "email": "cseligson4@ucla.edu",
        "Date_Of_Birth": "2/28/2009",
        "Age": 24,
        "Country": "Russia",
        "Phone": "2843908811"
    },
    {
        "id": 6,
        "first_name": "Isa",
        "last_name": "Olenchikov",
        "email": "iolenchikov5@over-blog.com",
        "Date_Of_Birth": "4/22/2001",
        "Age": 67,
        "Country": "China",
        "Phone": "4379092123"
    },
    {
        "id": 7,
        "first_name": "Alissa",
        "last_name": "Moyes",
        "email": "amoyes6@angelfire.com",
        "Date_Of_Birth": "7/26/1983",
        "Age": 70,
        "Country": "France",
        "Phone": "5814074524"
    },
    {
        "id": 8,
        "first_name": "Romain",
        "last_name": "Cholmondeley",
        "email": "rcholmondeley7@berkeley.edu",
        "Date_Of_Birth": "12/19/1981",
        "Age": 74,
        "Country": "Poland",
        "Phone": "6432856230"
    },
    {
        "id": 9,
        "first_name": "Xavier",
        "last_name": "Klisch",
        "email": "xklisch8@t.co",
        "Date_Of_Birth": "3/1/1991",
        "Age": 93,
        "Country": "Philippines",
        "Phone": "2002161510"
    },
    {
        "id": 10,
        "first_name": "Elyssa",
        "last_name": "Penhaligon",
        "email": "epenhaligon9@deliciousdays.com",
        "Date_Of_Birth": "2/22/2019",
        "Age": 25,
        "Country": "Indonesia",
        "Phone": "2477373435"
    },
    {
        "id": 11,
        "first_name": "Salomo",
        "last_name": "Deboick",
        "email": "sdeboicka@cbslocal.com",
        "Date_Of_Birth": "1/3/1980",
        "Age": 26,
        "Country": "Argentina",
        "Phone": "5682344153"
    },
    {
        "id": 12,
        "first_name": "Gradey",
        "last_name": "Frid",
        "email": "gfridb@oakley.com",
        "Date_Of_Birth": "8/15/1986",
        "Age": 58,
        "Country": "China",
        "Phone": "8034594575"
    },
    {
        "id": 13,
        "first_name": "Constance",
        "last_name": "Giacometti",
        "email": "cgiacomettic@europa.eu",
        "Date_Of_Birth": "9/2/2007",
        "Age": 50,
        "Country": "Papua New Guinea",
        "Phone": "3357829780"
    },
    {
        "id": 14,
        "first_name": "Aksel",
        "last_name": "Pelosi",
        "email": "apelosid@npr.org",
        "Date_Of_Birth": "1/26/1999",
        "Age": 23,
        "Country": "France",
        "Phone": "4717136492"
    },
    {
        "id": 15,
        "first_name": "Dianemarie",
        "last_name": "Gennerich",
        "email": "dgenneriche@yahoo.com",
        "Date_Of_Birth": "6/1/2014",
        "Age": 85,
        "Country": "China",
        "Phone": "8953710105"
    },
    {
        "id": 16,
        "first_name": "Brook",
        "last_name": "Campey",
        "email": "bcampeyf@walmart.com",
        "Date_Of_Birth": "4/8/1985",
        "Age": 86,
        "Country": "Nigeria",
        "Phone": "4877243452"
    },
    {
        "id": 17,
        "first_name": "Latashia",
        "last_name": "Bowdon",
        "email": "lbowdong@addthis.com",
        "Date_Of_Birth": "5/28/2015",
        "Age": 85,
        "Country": "Sweden",
        "Phone": "7273114871"
    },
    {
        "id": 18,
        "first_name": "Adams",
        "last_name": "Got",
        "email": "agoth@reddit.com",
        "Date_Of_Birth": "1/15/1978",
        "Age": 90,
        "Country": "Russia",
        "Phone": "8908246134"
    },
    {
        "id": 19,
        "first_name": "Alene",
        "last_name": "Olechnowicz",
        "email": "aolechnowiczi@tripod.com",
        "Date_Of_Birth": "10/9/2021",
        "Age": 72,
        "Country": "Indonesia",
        "Phone": "6034866590"
    },
    {
        "id": 20,
        "first_name": "Carlie",
        "last_name": "Carlet",
        "email": "ccarletj@marketwatch.com",
        "Date_Of_Birth": "3/23/1972",
        "Age": 58,
        "Country": "Brazil",
        "Phone": "6191757941"
    },
    {
        "id": 21,
        "first_name": "Myriam",
        "last_name": "Labrum",
        "email": "mlabrumk@livejournal.com",
        "Date_Of_Birth": "7/7/1982",
        "Age": 100,
        "Country": "Seychelles",
        "Phone": "6133980388"
    },
    {
        "id": 22,
        "first_name": "Valida",
        "last_name": "Stollman",
        "email": "vstollmanl@free.fr",
        "Date_Of_Birth": "1/18/2007",
        "Age": 64,
        "Country": "Brazil",
        "Phone": "5088607908"
    },
    {
        "id": 23,
        "first_name": "Keene",
        "last_name": "Rawle",
        "email": "krawlem@home.pl",
        "Date_Of_Birth": "3/8/1986",
        "Age": 39,
        "Country": "Panama",
        "Phone": "9729042950"
    },
    {
        "id": 24,
        "first_name": "Erastus",
        "last_name": "MacPaike",
        "email": "emacpaiken@ihg.com",
        "Date_Of_Birth": "5/16/1995",
        "Age": 52,
        "Country": "China",
        "Phone": "8902669516"
    },
    {
        "id": 25,
        "first_name": "Thadeus",
        "last_name": "Klosser",
        "email": "tklossero@usda.gov",
        "Date_Of_Birth": "5/8/2020",
        "Age": 42,
        "Country": "Poland",
        "Phone": "4873478190"
    },
    {
        "id": 26,
        "first_name": "Tarrance",
        "last_name": "Vearncomb",
        "email": "tvearncombp@digg.com",
        "Date_Of_Birth": "5/1/1991",
        "Age": 54,
        "Country": "Russia",
        "Phone": "1016965071"
    },
    {
        "id": 27,
        "first_name": "Adler",
        "last_name": "Kittow",
        "email": "akittowq@gnu.org",
        "Date_Of_Birth": "6/18/2021",
        "Age": 97,
        "Country": "United States",
        "Phone": "3162478268"
    },
    {
        "id": 28,
        "first_name": "Thayne",
        "last_name": "Quilkin",
        "email": "tquilkinr@vinaora.com",
        "Date_Of_Birth": "2/4/2009",
        "Age": 90,
        "Country": "Belarus",
        "Phone": "5743294309"
    },
    {
        "id": 29,
        "first_name": "Obadias",
        "last_name": "Cowitz",
        "email": "ocowitzs@godaddy.com",
        "Date_Of_Birth": "7/22/1972",
        "Age": 56,
        "Country": "Norway",
        "Phone": "7729696174"
    },
    {
        "id": 30,
        "first_name": "Goldi",
        "last_name": "Heliar",
        "email": "gheliart@google.es",
        "Date_Of_Birth": "3/28/1983",
        "Age": 77,
        "Country": "Portugal",
        "Phone": "3896303001"
    },
    {
        "id": 31,
        "first_name": "Fidela",
        "last_name": "Milstead",
        "email": "fmilsteadu@ameblo.jp",
        "Date_Of_Birth": "10/24/2018",
        "Age": 58,
        "Country": "Ukraine",
        "Phone": "1722781270"
    },
    {
        "id": 32,
        "first_name": "Wylma",
        "last_name": "Hawkeridge",
        "email": "whawkeridgev@over-blog.com",
        "Date_Of_Birth": "11/21/1987",
        "Age": 19,
        "Country": "France",
        "Phone": "7625639260"
    },
    {
        "id": 33,
        "first_name": "Merline",
        "last_name": "Grimsley",
        "email": "mgrimsleyw@bbc.co.uk",
        "Date_Of_Birth": "8/1/1976",
        "Age": 43,
        "Country": "Brazil",
        "Phone": "5992745451"
    },
    {
        "id": 34,
        "first_name": "Pryce",
        "last_name": "Tritton",
        "email": "ptrittonx@addtoany.com",
        "Date_Of_Birth": "7/17/1982",
        "Age": 57,
        "Country": "Sri Lanka",
        "Phone": "9584445698"
    },
    {
        "id": 35,
        "first_name": "Bibbye",
        "last_name": "Bambury",
        "email": "bbamburyy@deliciousdays.com",
        "Date_Of_Birth": "11/16/1978",
        "Age": 95,
        "Country": "Argentina",
        "Phone": "9365306708"
    },
    {
        "id": 36,
        "first_name": "Aylmar",
        "last_name": "Dodle",
        "email": "adodlez@amazon.co.jp",
        "Date_Of_Birth": "6/3/2001",
        "Age": 60,
        "Country": "Yemen",
        "Phone": "4771163553"
    },
    {
        "id": 37,
        "first_name": "Appolonia",
        "last_name": "Barks",
        "email": "abarks10@msn.com",
        "Date_Of_Birth": "2/16/2009",
        "Age": 94,
        "Country": "Spain",
        "Phone": "5361542388"
    },
    {
        "id": 38,
        "first_name": "Roth",
        "last_name": "Tumayan",
        "email": "rtumayan11@ustream.tv",
        "Date_Of_Birth": "5/4/1984",
        "Age": 57,
        "Country": "Indonesia",
        "Phone": "6649573290"
    },
    {
        "id": 39,
        "first_name": "Crichton",
        "last_name": "Abbotts",
        "email": "cabbotts12@t-online.de",
        "Date_Of_Birth": "7/23/1982",
        "Age": 33,
        "Country": "Philippines",
        "Phone": "4628814046"
    },
    {
        "id": 40,
        "first_name": "Thibaut",
        "last_name": "Harnetty",
        "email": "tharnetty13@aol.com",
        "Date_Of_Birth": "10/29/1980",
        "Age": 29,
        "Country": "Burkina Faso",
        "Phone": "8205729803"
    },
    {
        "id": 41,
        "first_name": "Patricio",
        "last_name": "Cann",
        "email": "pcann14@free.fr",
        "Date_Of_Birth": "2/7/2005",
        "Age": 49,
        "Country": "Indonesia",
        "Phone": "1574340084"
    },
    {
        "id": 42,
        "first_name": "Lacey",
        "last_name": "Rand",
        "email": "lrand15@desdev.cn",
        "Date_Of_Birth": "7/19/2015",
        "Age": 50,
        "Country": "Bosnia and Herzegovina",
        "Phone": "2289264234"
    },
    {
        "id": 43,
        "first_name": "Kimbell",
        "last_name": "Spaduzza",
        "email": "kspaduzza16@slate.com",
        "Date_Of_Birth": "4/25/2012",
        "Age": 42,
        "Country": "Portugal",
        "Phone": "6246884969"
    },
    {
        "id": 44,
        "first_name": "Valentine",
        "last_name": "Britten",
        "email": "vbritten17@g.co",
        "Date_Of_Birth": "4/15/2019",
        "Age": 35,
        "Country": "Brazil",
        "Phone": "4496894714"
    },
    {
        "id": 45,
        "first_name": "Zenia",
        "last_name": "Geleman",
        "email": "zgeleman18@narod.ru",
        "Date_Of_Birth": "10/26/1980",
        "Age": 32,
        "Country": "Poland",
        "Phone": "8384382082"
    },
    {
        "id": 46,
        "first_name": "Ferdy",
        "last_name": "Peddel",
        "email": "fpeddel19@barnesandnoble.com",
        "Date_Of_Birth": "4/7/1993",
        "Age": 25,
        "Country": "Latvia",
        "Phone": "7532071709"
    },
    {
        "id": 47,
        "first_name": "Asia",
        "last_name": "Osichev",
        "email": "aosichev1a@google.fr",
        "Date_Of_Birth": "11/30/1973",
        "Age": 70,
        "Country": "Thailand",
        "Phone": "1275782418"
    },
    {
        "id": 48,
        "first_name": "Cornelle",
        "last_name": "Ivashkin",
        "email": "civashkin1b@discuz.net",
        "Date_Of_Birth": "3/2/2013",
        "Age": 84,
        "Country": "Ukraine",
        "Phone": "8748155102"
    },
    {
        "id": 49,
        "first_name": "Arly",
        "last_name": "Grube",
        "email": "agrube1c@com.com",
        "Date_Of_Birth": "4/20/1985",
        "Age": 83,
        "Country": "China",
        "Phone": "2177534814"
    },
    {
        "id": 50,
        "first_name": "Keslie",
        "last_name": "Wanell",
        "email": "kwanell1d@unc.edu",
        "Date_Of_Birth": "5/3/1984",
        "Age": 25,
        "Country": "China",
        "Phone": "7538867970"
    },
    {
        "id": 51,
        "first_name": "Carlyle",
        "last_name": "Botting",
        "email": "cbotting1e@fema.gov",
        "Date_Of_Birth": "6/4/2010",
        "Age": 78,
        "Country": "France",
        "Phone": "6904446435"
    },
    {
        "id": 52,
        "first_name": "Clevey",
        "last_name": "Oles",
        "email": "coles1f@shareasale.com",
        "Date_Of_Birth": "9/16/2011",
        "Age": 100,
        "Country": "Indonesia",
        "Phone": "5429420052"
    },
    {
        "id": 53,
        "first_name": "Siffre",
        "last_name": "Brownbridge",
        "email": "sbrownbridge1g@istockphoto.com",
        "Date_Of_Birth": "5/14/2005",
        "Age": 90,
        "Country": "Namibia",
        "Phone": "6341935763"
    },
    {
        "id": 54,
        "first_name": "Sarine",
        "last_name": "Mennear",
        "email": "smennear1h@jigsy.com",
        "Date_Of_Birth": "5/21/1998",
        "Age": 38,
        "Country": "China",
        "Phone": "7676235072"
    },
    {
        "id": 55,
        "first_name": "Sherye",
        "last_name": "Melanaphy",
        "email": "smelanaphy1i@oaic.gov.au",
        "Date_Of_Birth": "3/28/2005",
        "Age": 54,
        "Country": "United States",
        "Phone": "9724862443"
    },
    {
        "id": 56,
        "first_name": "Lena",
        "last_name": "Friend",
        "email": "lfriend1j@mediafire.com",
        "Date_Of_Birth": "7/17/1999",
        "Age": 24,
        "Country": "Cape Verde",
        "Phone": "9186791421"
    },
    {
        "id": 57,
        "first_name": "Jolyn",
        "last_name": "O'Noulane",
        "email": "jonoulane1k@soup.io",
        "Date_Of_Birth": "11/17/2018",
        "Age": 28,
        "Country": "China",
        "Phone": "5888436292"
    },
    {
        "id": 58,
        "first_name": "Lucita",
        "last_name": "Brymner",
        "email": "lbrymner1l@tinypic.com",
        "Date_Of_Birth": "9/28/1983",
        "Age": 56,
        "Country": "China",
        "Phone": "5604701428"
    },
    {
        "id": 59,
        "first_name": "Sophronia",
        "last_name": "Davioud",
        "email": "sdavioud1m@tinypic.com",
        "Date_Of_Birth": "3/29/2018",
        "Age": 81,
        "Country": "Mexico",
        "Phone": "6218522612"
    },
    {
        "id": 60,
        "first_name": "Willow",
        "last_name": "Bloxholm",
        "email": "wbloxholm1n@slate.com",
        "Date_Of_Birth": "6/19/1987",
        "Age": 25,
        "Country": "Hungary",
        "Phone": "7799812093"
    },
    {
        "id": 61,
        "first_name": "Geoff",
        "last_name": "Bourtoumieux",
        "email": "gbourtoumieux1o@bloglovin.com",
        "Date_Of_Birth": "1/2/1997",
        "Age": 97,
        "Country": "Vietnam",
        "Phone": "5186887452"
    },
    {
        "id": 62,
        "first_name": "Marcelline",
        "last_name": "Sanchiz",
        "email": "msanchiz1p@webeden.co.uk",
        "Date_Of_Birth": "9/6/1986",
        "Age": 77,
        "Country": "Poland",
        "Phone": "6618552870"
    },
    {
        "id": 63,
        "first_name": "Sanford",
        "last_name": "Ducker",
        "email": "sducker1q@google.nl",
        "Date_Of_Birth": "2/6/1989",
        "Age": 94,
        "Country": "China",
        "Phone": "8538436734"
    },
    {
        "id": 64,
        "first_name": "Kelley",
        "last_name": "Worgan",
        "email": "kworgan1r@nasa.gov",
        "Date_Of_Birth": "8/3/1994",
        "Age": 34,
        "Country": "China",
        "Phone": "5388390724"
    },
    {
        "id": 65,
        "first_name": "Kerry",
        "last_name": "Yes",
        "email": "kyes1s@qq.com",
        "Date_Of_Birth": "1/21/1988",
        "Age": 58,
        "Country": "China",
        "Phone": "6515680204"
    },
    {
        "id": 66,
        "first_name": "Euphemia",
        "last_name": "Pilgram",
        "email": "epilgram1t@taobao.com",
        "Date_Of_Birth": "5/19/2003",
        "Age": 96,
        "Country": "Belarus",
        "Phone": "3357816569"
    },
    {
        "id": 67,
        "first_name": "Nathalia",
        "last_name": "Pascow",
        "email": "npascow1u@cbsnews.com",
        "Date_Of_Birth": "9/10/2009",
        "Age": 81,
        "Country": "Brazil",
        "Phone": "9276761567"
    },
    {
        "id": 68,
        "first_name": "Reta",
        "last_name": "Simonini",
        "email": "rsimonini1v@sphinn.com",
        "Date_Of_Birth": "9/26/1991",
        "Age": 28,
        "Country": "China",
        "Phone": "7343818572"
    },
    {
        "id": 69,
        "first_name": "Daffy",
        "last_name": "Jepps",
        "email": "djepps1w@google.com.br",
        "Date_Of_Birth": "8/18/1986",
        "Age": 92,
        "Country": "Indonesia",
        "Phone": "9199151777"
    },
    {
        "id": 70,
        "first_name": "Charlot",
        "last_name": "Connew",
        "email": "cconnew1x@so-net.ne.jp",
        "Date_Of_Birth": "8/31/1974",
        "Age": 62,
        "Country": "Portugal",
        "Phone": "5656534431"
    },
    {
        "id": 71,
        "first_name": "Ambrosius",
        "last_name": "Hopfner",
        "email": "ahopfner1y@ca.gov",
        "Date_Of_Birth": "11/5/2014",
        "Age": 78,
        "Country": "Malawi",
        "Phone": "3951594035"
    },
    {
        "id": 72,
        "first_name": "Bjorn",
        "last_name": "McGuire",
        "email": "bmcguire1z@rambler.ru",
        "Date_Of_Birth": "5/16/2003",
        "Age": 72,
        "Country": "Macao",
        "Phone": "3274335158"
    },
    {
        "id": 73,
        "first_name": "Elbertina",
        "last_name": "McGahern",
        "email": "emcgahern20@kickstarter.com",
        "Date_Of_Birth": "9/13/2001",
        "Age": 91,
        "Country": "Germany",
        "Phone": "2669789075"
    },
    {
        "id": 74,
        "first_name": "Lionel",
        "last_name": "Matelaitis",
        "email": "lmatelaitis21@stumbleupon.com",
        "Date_Of_Birth": "11/24/1981",
        "Age": 27,
        "Country": "Kyrgyzstan",
        "Phone": "3307034787"
    },
    {
        "id": 75,
        "first_name": "Sonia",
        "last_name": "O'Mullaney",
        "email": "somullaney22@columbia.edu",
        "Date_Of_Birth": "11/25/1975",
        "Age": 44,
        "Country": "Germany",
        "Phone": "4692097390"
    },
    {
        "id": 76,
        "first_name": "Clerkclaude",
        "last_name": "Sirey",
        "email": "csirey23@pcworld.com",
        "Date_Of_Birth": "6/2/1999",
        "Age": 20,
        "Country": "Brazil",
        "Phone": "5351802794"
    },
    {
        "id": 77,
        "first_name": "Merrili",
        "last_name": "Pyer",
        "email": "mpyer24@army.mil",
        "Date_Of_Birth": "3/5/1982",
        "Age": 86,
        "Country": "China",
        "Phone": "7252134350"
    },
    {
        "id": 78,
        "first_name": "Daryn",
        "last_name": "Shurman",
        "email": "dshurman25@gmpg.org",
        "Date_Of_Birth": "9/7/2006",
        "Age": 80,
        "Country": "Azerbaijan",
        "Phone": "7355933974"
    },
    {
        "id": 79,
        "first_name": "Tanhya",
        "last_name": "Schwerin",
        "email": "tschwerin26@globo.com",
        "Date_Of_Birth": "11/10/2009",
        "Age": 69,
        "Country": "Portugal",
        "Phone": "9582091477"
    },
    {
        "id": 80,
        "first_name": "Newton",
        "last_name": "Twells",
        "email": "ntwells27@hud.gov",
        "Date_Of_Birth": "7/7/1971",
        "Age": 19,
        "Country": "Indonesia",
        "Phone": "2562350494"
    },
    {
        "id": 81,
        "first_name": "Kiele",
        "last_name": "Tipler",
        "email": "ktipler28@telegraph.co.uk",
        "Date_Of_Birth": "12/20/1975",
        "Age": 78,
        "Country": "China",
        "Phone": "7526291035"
    },
    {
        "id": 82,
        "first_name": "Dani",
        "last_name": "Champney",
        "email": "dchampney29@sphinn.com",
        "Date_Of_Birth": "12/19/1996",
        "Age": 75,
        "Country": "Poland",
        "Phone": "7235307066"
    },
    {
        "id": 83,
        "first_name": "Wallas",
        "last_name": "Churchouse",
        "email": "wchurchouse2a@istockphoto.com",
        "Date_Of_Birth": "5/20/1978",
        "Age": 93,
        "Country": "Ukraine",
        "Phone": "4608763091"
    },
    {
        "id": 84,
        "first_name": "Joli",
        "last_name": "Tilberry",
        "email": "jtilberry2b@lycos.com",
        "Date_Of_Birth": "2/26/1974",
        "Age": 49,
        "Country": "Philippines",
        "Phone": "7036176726"
    },
    {
        "id": 85,
        "first_name": "Ardis",
        "last_name": "Bollini",
        "email": "abollini2c@flavors.me",
        "Date_Of_Birth": "3/21/1977",
        "Age": 84,
        "Country": "Philippines",
        "Phone": "4547779441"
    },
    {
        "id": 86,
        "first_name": "Raff",
        "last_name": "Astles",
        "email": "rastles2d@weather.com",
        "Date_Of_Birth": "7/30/2001",
        "Age": 74,
        "Country": "Ukraine",
        "Phone": "6003024496"
    },
    {
        "id": 87,
        "first_name": "Delphinia",
        "last_name": "Storcke",
        "email": "dstorcke2e@dailymotion.com",
        "Date_Of_Birth": "5/24/2000",
        "Age": 90,
        "Country": "Cuba",
        "Phone": "1927670929"
    },
    {
        "id": 88,
        "first_name": "Herrick",
        "last_name": "Tuther",
        "email": "htuther2f@spiegel.de",
        "Date_Of_Birth": "3/20/1994",
        "Age": 65,
        "Country": "Indonesia",
        "Phone": "2772744520"
    },
    {
        "id": 89,
        "first_name": "Raine",
        "last_name": "Paraman",
        "email": "rparaman2g@merriam-webster.com",
        "Date_Of_Birth": "3/7/1980",
        "Age": 55,
        "Country": "Philippines",
        "Phone": "4626984951"
    },
    {
        "id": 90,
        "first_name": "Tarrah",
        "last_name": "Kibby",
        "email": "tkibby2h@princeton.edu",
        "Date_Of_Birth": "5/28/1992",
        "Age": 55,
        "Country": "United States",
        "Phone": "6193343947"
    },
    {
        "id": 91,
        "first_name": "Hewie",
        "last_name": "Ghidoni",
        "email": "hghidoni2i@nyu.edu",
        "Date_Of_Birth": "10/29/1983",
        "Age": 43,
        "Country": "Tunisia",
        "Phone": "9089951265"
    },
    {
        "id": 92,
        "first_name": "Say",
        "last_name": "Harler",
        "email": "sharler2j@youtube.com",
        "Date_Of_Birth": "3/18/2017",
        "Age": 33,
        "Country": "China",
        "Phone": "5083526607"
    },
    {
        "id": 93,
        "first_name": "Dulce",
        "last_name": "Chafer",
        "email": "dchafer2k@youtube.com",
        "Date_Of_Birth": "4/21/1978",
        "Age": 66,
        "Country": "Croatia",
        "Phone": "3677943386"
    },
    {
        "id": 94,
        "first_name": "Joya",
        "last_name": "Tibb",
        "email": "jtibb2l@mayoclinic.com",
        "Date_Of_Birth": "8/12/1974",
        "Age": 99,
        "Country": "China",
        "Phone": "8535659373"
    },
    {
        "id": 95,
        "first_name": "Angelia",
        "last_name": "McGilvray",
        "email": "amcgilvray2m@uiuc.edu",
        "Date_Of_Birth": "8/8/2006",
        "Age": 90,
        "Country": "Poland",
        "Phone": "7088798737"
    },
    {
        "id": 96,
        "first_name": "Emalia",
        "last_name": "Allingham",
        "email": "eallingham2n@ted.com",
        "Date_Of_Birth": "3/20/1998",
        "Age": 89,
        "Country": "Greece",
        "Phone": "5928414452"
    },
    {
        "id": 97,
        "first_name": "Ivette",
        "last_name": "Bradwell",
        "email": "ibradwell2o@ning.com",
        "Date_Of_Birth": "9/16/1978",
        "Age": 72,
        "Country": "Vietnam",
        "Phone": "2305144488"
    },
    {
        "id": 98,
        "first_name": "Brenn",
        "last_name": "St. Hill",
        "email": "bsthill2p@addtoany.com",
        "Date_Of_Birth": "11/15/1998",
        "Age": 67,
        "Country": "Russia",
        "Phone": "6615771321"
    },
    {
        "id": 99,
        "first_name": "Ingra",
        "last_name": "Gravenell",
        "email": "igravenell2q@google.fr",
        "Date_Of_Birth": "12/19/2021",
        "Age": 74,
        "Country": "China",
        "Phone": "1478161399"
    },
    {
        "id": 100,
        "first_name": "Binni",
        "last_name": "Kingett",
        "email": "bkingett2r@forbes.com",
        "Date_Of_Birth": "1/2/2013",
        "Age": 30,
        "Country": "Russia",
        "Phone": "6981996620"
    },
    {
        "id": 101,
        "first_name": "Lenora",
        "last_name": "Laing",
        "email": "llaing2s@lycos.com",
        "Date_Of_Birth": "7/8/1980",
        "Age": 96,
        "Country": "China",
        "Phone": "1977592657"
    },
    {
        "id": 102,
        "first_name": "Morganica",
        "last_name": "Humberstone",
        "email": "mhumberstone2t@cnn.com",
        "Date_Of_Birth": "4/5/1987",
        "Age": 75,
        "Country": "China",
        "Phone": "5134119688"
    },
    {
        "id": 103,
        "first_name": "Dunstan",
        "last_name": "Girardini",
        "email": "dgirardini2u@biglobe.ne.jp",
        "Date_Of_Birth": "11/12/1979",
        "Age": 21,
        "Country": "Nigeria",
        "Phone": "4783392394"
    },
    {
        "id": 104,
        "first_name": "Marven",
        "last_name": "Laven",
        "email": "mlaven2v@ezinearticles.com",
        "Date_Of_Birth": "9/23/1970",
        "Age": 94,
        "Country": "Indonesia",
        "Phone": "7237364607"
    },
    {
        "id": 105,
        "first_name": "Baudoin",
        "last_name": "Attrill",
        "email": "battrill2w@oaic.gov.au",
        "Date_Of_Birth": "11/24/1998",
        "Age": 39,
        "Country": "China",
        "Phone": "8469436114"
    },
    {
        "id": 106,
        "first_name": "Madeline",
        "last_name": "Clixby",
        "email": "mclixby2x@tiny.cc",
        "Date_Of_Birth": "10/17/1971",
        "Age": 30,
        "Country": "Indonesia",
        "Phone": "9402504504"
    },
    {
        "id": 107,
        "first_name": "Lydia",
        "last_name": "Overnell",
        "email": "lovernell2y@washington.edu",
        "Date_Of_Birth": "6/13/2010",
        "Age": 79,
        "Country": "China",
        "Phone": "5035330325"
    },
    {
        "id": 108,
        "first_name": "Rosaleen",
        "last_name": "Duiged",
        "email": "rduiged2z@ed.gov",
        "Date_Of_Birth": "11/13/1975",
        "Age": 97,
        "Country": "Colombia",
        "Phone": "5061609247"
    },
    {
        "id": 109,
        "first_name": "Zak",
        "last_name": "Blune",
        "email": "zblune30@craigslist.org",
        "Date_Of_Birth": "12/16/2011",
        "Age": 88,
        "Country": "Japan",
        "Phone": "8615810741"
    },
    {
        "id": 110,
        "first_name": "Amelita",
        "last_name": "Shalliker",
        "email": "ashalliker31@stanford.edu",
        "Date_Of_Birth": "8/16/1997",
        "Age": 91,
        "Country": "Cameroon",
        "Phone": "9544733353"
    },
    {
        "id": 111,
        "first_name": "Carver",
        "last_name": "Norvel",
        "email": "cnorvel32@wikimedia.org",
        "Date_Of_Birth": "10/9/2015",
        "Age": 77,
        "Country": "Portugal",
        "Phone": "1782244335"
    },
    {
        "id": 112,
        "first_name": "Zelda",
        "last_name": "Aingell",
        "email": "zaingell33@nydailynews.com",
        "Date_Of_Birth": "8/5/2022",
        "Age": 29,
        "Country": "China",
        "Phone": "2862457868"
    },
    {
        "id": 113,
        "first_name": "Andrus",
        "last_name": "Plesing",
        "email": "aplesing34@google.cn",
        "Date_Of_Birth": "12/6/1994",
        "Age": 92,
        "Country": "Philippines",
        "Phone": "6028094001"
    },
    {
        "id": 114,
        "first_name": "Gustavus",
        "last_name": "Coulthard",
        "email": "gcoulthard35@toplist.cz",
        "Date_Of_Birth": "8/8/1981",
        "Age": 27,
        "Country": "France",
        "Phone": "7011510459"
    },
    {
        "id": 115,
        "first_name": "Gonzalo",
        "last_name": "Frankom",
        "email": "gfrankom36@tuttocitta.it",
        "Date_Of_Birth": "3/1/1973",
        "Age": 43,
        "Country": "Mexico",
        "Phone": "8661089251"
    },
    {
        "id": 116,
        "first_name": "Theodora",
        "last_name": "Olliff",
        "email": "tolliff37@imageshack.us",
        "Date_Of_Birth": "2/17/2003",
        "Age": 55,
        "Country": "Peru",
        "Phone": "6956472065"
    },
    {
        "id": 117,
        "first_name": "Immanuel",
        "last_name": "Coxwell",
        "email": "icoxwell38@patch.com",
        "Date_Of_Birth": "4/26/1991",
        "Age": 55,
        "Country": "Philippines",
        "Phone": "4415938510"
    },
    {
        "id": 118,
        "first_name": "Morley",
        "last_name": "Reap",
        "email": "mreap39@webs.com",
        "Date_Of_Birth": "7/2/1987",
        "Age": 18,
        "Country": "Ukraine",
        "Phone": "7756986494"
    },
    {
        "id": 119,
        "first_name": "Gracia",
        "last_name": "Swaby",
        "email": "gswaby3a@infoseek.co.jp",
        "Date_Of_Birth": "3/21/1988",
        "Age": 75,
        "Country": "United States",
        "Phone": "6097702914"
    },
    {
        "id": 120,
        "first_name": "Timothea",
        "last_name": "Friatt",
        "email": "tfriatt3b@pen.io",
        "Date_Of_Birth": "7/15/1998",
        "Age": 47,
        "Country": "China",
        "Phone": "2062006364"
    },
    {
        "id": 121,
        "first_name": "Bethena",
        "last_name": "Empringham",
        "email": "bempringham3c@cbc.ca",
        "Date_Of_Birth": "10/10/2020",
        "Age": 20,
        "Country": "Vietnam",
        "Phone": "6478069489"
    },
    {
        "id": 122,
        "first_name": "Say",
        "last_name": "Cheese",
        "email": "scheese3d@wordpress.org",
        "Date_Of_Birth": "12/7/2018",
        "Age": 59,
        "Country": "Yemen",
        "Phone": "1913839337"
    },
    {
        "id": 123,
        "first_name": "Welch",
        "last_name": "Cowton",
        "email": "wcowton3e@ted.com",
        "Date_Of_Birth": "1/28/2018",
        "Age": 64,
        "Country": "Indonesia",
        "Phone": "9527431821"
    },
    {
        "id": 124,
        "first_name": "Morey",
        "last_name": "But",
        "email": "mbut3f@eepurl.com",
        "Date_Of_Birth": "11/8/2002",
        "Age": 44,
        "Country": "Sweden",
        "Phone": "8747166053"
    },
    {
        "id": 125,
        "first_name": "Dale",
        "last_name": "Lattos",
        "email": "dlattos3g@wikipedia.org",
        "Date_Of_Birth": "1/25/1985",
        "Age": 39,
        "Country": "Canada",
        "Phone": "7508661967"
    },
    {
        "id": 126,
        "first_name": "Giulia",
        "last_name": "Scudder",
        "email": "gscudder3h@loc.gov",
        "Date_Of_Birth": "2/16/2012",
        "Age": 21,
        "Country": "Thailand",
        "Phone": "2346839152"
    },
    {
        "id": 127,
        "first_name": "Kala",
        "last_name": "Fuxman",
        "email": "kfuxman3i@wisc.edu",
        "Date_Of_Birth": "7/7/2000",
        "Age": 92,
        "Country": "Dominican Republic",
        "Phone": "7344472347"
    },
    {
        "id": 128,
        "first_name": "Claudian",
        "last_name": "Harkus",
        "email": "charkus3j@harvard.edu",
        "Date_Of_Birth": "5/3/1983",
        "Age": 97,
        "Country": "Poland",
        "Phone": "9078125052"
    },
    {
        "id": 129,
        "first_name": "Gunar",
        "last_name": "Dade",
        "email": "gdade3k@whitehouse.gov",
        "Date_Of_Birth": "9/8/2001",
        "Age": 91,
        "Country": "Tajikistan",
        "Phone": "1386489951"
    },
    {
        "id": 130,
        "first_name": "Carlen",
        "last_name": "Quinsee",
        "email": "cquinsee3l@ycombinator.com",
        "Date_Of_Birth": "2/4/1978",
        "Age": 30,
        "Country": "Indonesia",
        "Phone": "8248097163"
    },
    {
        "id": 131,
        "first_name": "Kalinda",
        "last_name": "Dearell",
        "email": "kdearell3m@netvibes.com",
        "Date_Of_Birth": "7/31/1989",
        "Age": 32,
        "Country": "China",
        "Phone": "4889297075"
    },
    {
        "id": 132,
        "first_name": "Brigham",
        "last_name": "Leaburn",
        "email": "bleaburn3n@ebay.com",
        "Date_Of_Birth": "2/29/1984",
        "Age": 93,
        "Country": "Indonesia",
        "Phone": "7778068084"
    },
    {
        "id": 133,
        "first_name": "Nickolaus",
        "last_name": "Tunsley",
        "email": "ntunsley3o@statcounter.com",
        "Date_Of_Birth": "4/18/2010",
        "Age": 99,
        "Country": "France",
        "Phone": "1781128734"
    },
    {
        "id": 134,
        "first_name": "Adelina",
        "last_name": "Eaken",
        "email": "aeaken3p@biglobe.ne.jp",
        "Date_Of_Birth": "3/21/1994",
        "Age": 96,
        "Country": "Thailand",
        "Phone": "8021486615"
    },
    {
        "id": 135,
        "first_name": "Aimee",
        "last_name": "Semark",
        "email": "asemark3q@cdbaby.com",
        "Date_Of_Birth": "8/4/1971",
        "Age": 88,
        "Country": "Brazil",
        "Phone": "9556293146"
    },
    {
        "id": 136,
        "first_name": "Langsdon",
        "last_name": "Blenkinsopp",
        "email": "lblenkinsopp3r@dailymail.co.uk",
        "Date_Of_Birth": "12/13/2018",
        "Age": 81,
        "Country": "Vietnam",
        "Phone": "7442344485"
    },
    {
        "id": 137,
        "first_name": "Elinore",
        "last_name": "Cheesley",
        "email": "echeesley3s@redcross.org",
        "Date_Of_Birth": "7/2/1998",
        "Age": 38,
        "Country": "China",
        "Phone": "4944004968"
    },
    {
        "id": 138,
        "first_name": "Kean",
        "last_name": "Keemer",
        "email": "kkeemer3t@reuters.com",
        "Date_Of_Birth": "3/17/1976",
        "Age": 58,
        "Country": "Peru",
        "Phone": "7095257490"
    },
    {
        "id": 139,
        "first_name": "Donny",
        "last_name": "Tesmond",
        "email": "dtesmond3u@booking.com",
        "Date_Of_Birth": "12/13/1987",
        "Age": 77,
        "Country": "China",
        "Phone": "9632642363"
    },
    {
        "id": 140,
        "first_name": "Remus",
        "last_name": "Mardle",
        "email": "rmardle3v@weather.com",
        "Date_Of_Birth": "4/24/1978",
        "Age": 35,
        "Country": "Russia",
        "Phone": "4698043558"
    },
    {
        "id": 141,
        "first_name": "Torin",
        "last_name": "Kester",
        "email": "tkester3w@hao123.com",
        "Date_Of_Birth": "11/8/1989",
        "Age": 24,
        "Country": "Indonesia",
        "Phone": "2827814064"
    },
    {
        "id": 142,
        "first_name": "Arlee",
        "last_name": "MacMickan",
        "email": "amacmickan3x@npr.org",
        "Date_Of_Birth": "8/6/1971",
        "Age": 58,
        "Country": "China",
        "Phone": "4187036922"
    },
    {
        "id": 143,
        "first_name": "Wilfred",
        "last_name": "Lindores",
        "email": "wlindores3y@virginia.edu",
        "Date_Of_Birth": "11/30/1988",
        "Age": 78,
        "Country": "Russia",
        "Phone": "1248791030"
    },
    {
        "id": 144,
        "first_name": "Albert",
        "last_name": "Bancroft",
        "email": "abancroft3z@1688.com",
        "Date_Of_Birth": "11/28/1991",
        "Age": 22,
        "Country": "Venezuela",
        "Phone": "1557185887"
    },
    {
        "id": 145,
        "first_name": "Correna",
        "last_name": "Ebbles",
        "email": "cebbles40@nyu.edu",
        "Date_Of_Birth": "4/18/2008",
        "Age": 82,
        "Country": "Venezuela",
        "Phone": "3197473190"
    },
    {
        "id": 146,
        "first_name": "Desmond",
        "last_name": "Lucey",
        "email": "dlucey41@squidoo.com",
        "Date_Of_Birth": "10/30/2015",
        "Age": 96,
        "Country": "Japan",
        "Phone": "3543689517"
    },
    {
        "id": 147,
        "first_name": "Ernesto",
        "last_name": "Dutnell",
        "email": "edutnell42@cdbaby.com",
        "Date_Of_Birth": "8/9/1975",
        "Age": 76,
        "Country": "Tunisia",
        "Phone": "5186512561"
    },
    {
        "id": 148,
        "first_name": "Nicholas",
        "last_name": "Codling",
        "email": "ncodling43@ebay.com",
        "Date_Of_Birth": "11/25/1974",
        "Age": 47,
        "Country": "Czech Republic",
        "Phone": "9309463928"
    },
    {
        "id": 149,
        "first_name": "Tasia",
        "last_name": "Cubbini",
        "email": "tcubbini44@w3.org",
        "Date_Of_Birth": "4/5/2012",
        "Age": 36,
        "Country": "Russia",
        "Phone": "4486298549"
    },
    {
        "id": 150,
        "first_name": "Glenna",
        "last_name": "Radborne",
        "email": "gradborne45@vimeo.com",
        "Date_Of_Birth": "5/21/2005",
        "Age": 54,
        "Country": "Portugal",
        "Phone": "3507613700"
    },
    {
        "id": 151,
        "first_name": "Molli",
        "last_name": "Grigor",
        "email": "mgrigor46@thetimes.co.uk",
        "Date_Of_Birth": "6/8/1981",
        "Age": 71,
        "Country": "Brazil",
        "Phone": "1698922903"
    },
    {
        "id": 152,
        "first_name": "Gerry",
        "last_name": "Davydochkin",
        "email": "gdavydochkin47@princeton.edu",
        "Date_Of_Birth": "9/12/2002",
        "Age": 21,
        "Country": "Russia",
        "Phone": "4438340625"
    },
    {
        "id": 153,
        "first_name": "Farrell",
        "last_name": "Kenion",
        "email": "fkenion48@wunderground.com",
        "Date_Of_Birth": "2/24/2006",
        "Age": 83,
        "Country": "Angola",
        "Phone": "2616981742"
    },
    {
        "id": 154,
        "first_name": "Laurette",
        "last_name": "Bramo",
        "email": "lbramo49@cnet.com",
        "Date_Of_Birth": "2/9/2007",
        "Age": 24,
        "Country": "China",
        "Phone": "1889828903"
    },
    {
        "id": 155,
        "first_name": "Joni",
        "last_name": "Ruggieri",
        "email": "jruggieri4a@360.cn",
        "Date_Of_Birth": "5/15/2018",
        "Age": 65,
        "Country": "Indonesia",
        "Phone": "4103744866"
    },
    {
        "id": 156,
        "first_name": "Sophia",
        "last_name": "Effaunt",
        "email": "seffaunt4b@angelfire.com",
        "Date_Of_Birth": "5/30/2014",
        "Age": 48,
        "Country": "Morocco",
        "Phone": "9796992157"
    },
    {
        "id": 157,
        "first_name": "Hyacintha",
        "last_name": "Clears",
        "email": "hclears4c@studiopress.com",
        "Date_Of_Birth": "10/9/1981",
        "Age": 59,
        "Country": "Mongolia",
        "Phone": "2208352006"
    },
    {
        "id": 158,
        "first_name": "Wilie",
        "last_name": "Deevey",
        "email": "wdeevey4d@narod.ru",
        "Date_Of_Birth": "8/20/1983",
        "Age": 59,
        "Country": "Serbia",
        "Phone": "9184710322"
    },
    {
        "id": 159,
        "first_name": "Berny",
        "last_name": "Reardon",
        "email": "breardon4e@dagondesign.com",
        "Date_Of_Birth": "10/1/2006",
        "Age": 42,
        "Country": "Cuba",
        "Phone": "4658565874"
    },
    {
        "id": 160,
        "first_name": "Sasha",
        "last_name": "Lavens",
        "email": "slavens4f@usda.gov",
        "Date_Of_Birth": "9/27/2007",
        "Age": 42,
        "Country": "China",
        "Phone": "6925602213"
    },
    {
        "id": 161,
        "first_name": "Cristen",
        "last_name": "Rickets",
        "email": "crickets4g@google.nl",
        "Date_Of_Birth": "9/30/2021",
        "Age": 59,
        "Country": "Indonesia",
        "Phone": "6525823005"
    },
    {
        "id": 162,
        "first_name": "Sim",
        "last_name": "Wrightham",
        "email": "swrightham4h@flavors.me",
        "Date_Of_Birth": "5/30/2013",
        "Age": 73,
        "Country": "Poland",
        "Phone": "2979560790"
    },
    {
        "id": 163,
        "first_name": "Mozelle",
        "last_name": "Henbury",
        "email": "mhenbury4i@ow.ly",
        "Date_Of_Birth": "3/8/1981",
        "Age": 94,
        "Country": "Mexico",
        "Phone": "9381604270"
    },
    {
        "id": 164,
        "first_name": "Guthrie",
        "last_name": "Munks",
        "email": "gmunks4j@cam.ac.uk",
        "Date_Of_Birth": "12/27/1989",
        "Age": 63,
        "Country": "China",
        "Phone": "8638350908"
    },
    {
        "id": 165,
        "first_name": "Corie",
        "last_name": "Robinson",
        "email": "crobinson4k@wired.com",
        "Date_Of_Birth": "9/2/1993",
        "Age": 35,
        "Country": "Greece",
        "Phone": "9977750162"
    },
    {
        "id": 166,
        "first_name": "Freeman",
        "last_name": "Stobbie",
        "email": "fstobbie4l@diigo.com",
        "Date_Of_Birth": "4/9/2022",
        "Age": 70,
        "Country": "China",
        "Phone": "3921924302"
    },
    {
        "id": 167,
        "first_name": "Jania",
        "last_name": "Tinn",
        "email": "jtinn4m@guardian.co.uk",
        "Date_Of_Birth": "9/27/1988",
        "Age": 66,
        "Country": "China",
        "Phone": "4985527180"
    },
    {
        "id": 168,
        "first_name": "Agustin",
        "last_name": "Claussen",
        "email": "aclaussen4n@smh.com.au",
        "Date_Of_Birth": "11/4/1974",
        "Age": 41,
        "Country": "Vietnam",
        "Phone": "5738226476"
    },
    {
        "id": 169,
        "first_name": "Vale",
        "last_name": "Keast",
        "email": "vkeast4o@nsw.gov.au",
        "Date_Of_Birth": "11/27/2000",
        "Age": 93,
        "Country": "Netherlands",
        "Phone": "5009697100"
    },
    {
        "id": 170,
        "first_name": "Jacinthe",
        "last_name": "Woltman",
        "email": "jwoltman4p@clickbank.net",
        "Date_Of_Birth": "3/21/2018",
        "Age": 97,
        "Country": "Philippines",
        "Phone": "4437283637"
    },
    {
        "id": 171,
        "first_name": "Blythe",
        "last_name": "Borrill",
        "email": "bborrill4q@europa.eu",
        "Date_Of_Birth": "8/3/2019",
        "Age": 26,
        "Country": "China",
        "Phone": "6386833668"
    },
    {
        "id": 172,
        "first_name": "Whit",
        "last_name": "Wilmott",
        "email": "wwilmott4r@mapy.cz",
        "Date_Of_Birth": "5/28/1986",
        "Age": 26,
        "Country": "Kazakhstan",
        "Phone": "3783560616"
    },
    {
        "id": 173,
        "first_name": "Mic",
        "last_name": "Sherrett",
        "email": "msherrett4s@amazon.com",
        "Date_Of_Birth": "4/2/1971",
        "Age": 93,
        "Country": "Russia",
        "Phone": "1506461359"
    },
    {
        "id": 174,
        "first_name": "Nonah",
        "last_name": "Banasik",
        "email": "nbanasik4t@mayoclinic.com",
        "Date_Of_Birth": "6/7/1983",
        "Age": 24,
        "Country": "Guinea",
        "Phone": "9421610225"
    },
    {
        "id": 175,
        "first_name": "Heindrick",
        "last_name": "Boissier",
        "email": "hboissier4u@nymag.com",
        "Date_Of_Birth": "3/14/2022",
        "Age": 95,
        "Country": "China",
        "Phone": "4568716005"
    },
    {
        "id": 176,
        "first_name": "Ayn",
        "last_name": "Van der Kruijs",
        "email": "avanderkruijs4v@domainmarket.com",
        "Date_Of_Birth": "8/28/1989",
        "Age": 94,
        "Country": "Thailand",
        "Phone": "2902060469"
    },
    {
        "id": 177,
        "first_name": "Ashien",
        "last_name": "Tomovic",
        "email": "atomovic4w@cdbaby.com",
        "Date_Of_Birth": "10/15/2010",
        "Age": 50,
        "Country": "Sweden",
        "Phone": "3454518880"
    },
    {
        "id": 178,
        "first_name": "Sean",
        "last_name": "Gunningham",
        "email": "sgunningham4x@ihg.com",
        "Date_Of_Birth": "8/27/1983",
        "Age": 95,
        "Country": "Poland",
        "Phone": "8219508913"
    },
    {
        "id": 179,
        "first_name": "Stacie",
        "last_name": "Gane",
        "email": "sgane4y@globo.com",
        "Date_Of_Birth": "4/20/1982",
        "Age": 31,
        "Country": "Portugal",
        "Phone": "7223124514"
    },
    {
        "id": 180,
        "first_name": "Lenna",
        "last_name": "Epp",
        "email": "lepp4z@squarespace.com",
        "Date_Of_Birth": "3/5/1977",
        "Age": 32,
        "Country": "Russia",
        "Phone": "1595779098"
    },
    {
        "id": 181,
        "first_name": "Veronique",
        "last_name": "Leverson",
        "email": "vleverson50@va.gov",
        "Date_Of_Birth": "6/28/1981",
        "Age": 24,
        "Country": "Thailand",
        "Phone": "1992895460"
    },
    {
        "id": 182,
        "first_name": "Samuel",
        "last_name": "Creegan",
        "email": "screegan51@bizjournals.com",
        "Date_Of_Birth": "10/28/2003",
        "Age": 21,
        "Country": "Thailand",
        "Phone": "4663117867"
    },
    {
        "id": 183,
        "first_name": "Luciano",
        "last_name": "Gilardengo",
        "email": "lgilardengo52@merriam-webster.com",
        "Date_Of_Birth": "7/5/1982",
        "Age": 97,
        "Country": "Poland",
        "Phone": "9605963568"
    },
    {
        "id": 184,
        "first_name": "Silvester",
        "last_name": "Pedlow",
        "email": "spedlow53@amazonaws.com",
        "Date_Of_Birth": "8/11/1978",
        "Age": 74,
        "Country": "Portugal",
        "Phone": "1455971135"
    },
    {
        "id": 185,
        "first_name": "Ado",
        "last_name": "Oliver-Paull",
        "email": "aoliverpaull54@webmd.com",
        "Date_Of_Birth": "11/5/2014",
        "Age": 95,
        "Country": "Russia",
        "Phone": "5515715523"
    },
    {
        "id": 186,
        "first_name": "Berty",
        "last_name": "Blondel",
        "email": "bblondel55@over-blog.com",
        "Date_Of_Birth": "8/1/1982",
        "Age": 23,
        "Country": "Sweden",
        "Phone": "5801822551"
    },
    {
        "id": 187,
        "first_name": "Jehanna",
        "last_name": "Jorden",
        "email": "jjorden56@oracle.com",
        "Date_Of_Birth": "1/4/1975",
        "Age": 87,
        "Country": "Paraguay",
        "Phone": "2124070518"
    },
    {
        "id": 188,
        "first_name": "Melessa",
        "last_name": "Stoak",
        "email": "mstoak57@surveymonkey.com",
        "Date_Of_Birth": "9/3/2010",
        "Age": 81,
        "Country": "Northern Mariana Islands",
        "Phone": "9389911258"
    },
    {
        "id": 189,
        "first_name": "Christine",
        "last_name": "Odney",
        "email": "codney58@psu.edu",
        "Date_Of_Birth": "4/25/1993",
        "Age": 100,
        "Country": "Peru",
        "Phone": "7566787158"
    },
    {
        "id": 190,
        "first_name": "Bernarr",
        "last_name": "Peggrem",
        "email": "bpeggrem59@google.de",
        "Date_Of_Birth": "6/5/1996",
        "Age": 61,
        "Country": "South Africa",
        "Phone": "1525608314"
    },
    {
        "id": 191,
        "first_name": "Lucina",
        "last_name": "Youings",
        "email": "lyouings5a@vistaprint.com",
        "Date_Of_Birth": "3/13/2007",
        "Age": 45,
        "Country": "China",
        "Phone": "1239850925"
    },
    {
        "id": 192,
        "first_name": "Bertrand",
        "last_name": "Peet",
        "email": "bpeet5b@howstuffworks.com",
        "Date_Of_Birth": "5/9/2013",
        "Age": 61,
        "Country": "Malta",
        "Phone": "3427770402"
    },
    {
        "id": 193,
        "first_name": "Freda",
        "last_name": "Munehay",
        "email": "fmunehay5c@twitter.com",
        "Date_Of_Birth": "3/25/1986",
        "Age": 99,
        "Country": "China",
        "Phone": "3015798824"
    },
    {
        "id": 194,
        "first_name": "Berty",
        "last_name": "Rospars",
        "email": "brospars5d@businessweek.com",
        "Date_Of_Birth": "11/15/1979",
        "Age": 43,
        "Country": "Finland",
        "Phone": "2868341905"
    },
    {
        "id": 195,
        "first_name": "Wren",
        "last_name": "Guyers",
        "email": "wguyers5e@networkadvertising.org",
        "Date_Of_Birth": "10/3/2013",
        "Age": 26,
        "Country": "Argentina",
        "Phone": "3072994942"
    },
    {
        "id": 196,
        "first_name": "Brennen",
        "last_name": "Stansby",
        "email": "bstansby5f@biglobe.ne.jp",
        "Date_Of_Birth": "12/7/2003",
        "Age": 23,
        "Country": "Iran",
        "Phone": "8988240902"
    },
    {
        "id": 197,
        "first_name": "Elwood",
        "last_name": "Colthurst",
        "email": "ecolthurst5g@soup.io",
        "Date_Of_Birth": "5/22/1997",
        "Age": 92,
        "Country": "United States",
        "Phone": "9492239165"
    },
    {
        "id": 198,
        "first_name": "Feodora",
        "last_name": "Borman",
        "email": "fborman5h@homestead.com",
        "Date_Of_Birth": "6/3/1974",
        "Age": 97,
        "Country": "Philippines",
        "Phone": "5702778759"
    },
    {
        "id": 199,
        "first_name": "Pris",
        "last_name": "Rosindill",
        "email": "prosindill5i@qq.com",
        "Date_Of_Birth": "4/4/2014",
        "Age": 39,
        "Country": "Belarus",
        "Phone": "3354825510"
    },
    {
        "id": 200,
        "first_name": "Kalil",
        "last_name": "Freckelton",
        "email": "kfreckelton5j@paginegialle.it",
        "Date_Of_Birth": "8/22/2015",
        "Age": 19,
        "Country": "China",
        "Phone": "8819567247"
    }
]